potsim2-0.3.6.dist-info/top_level.txt
potsim2-0.3.6.dist-info/RECORD
potsim2-0.3.6.dist-info/LICENSE
potsim2-0.3.6.dist-info/METADATA
potsim2-0.3.6.dist-info/WHEEL
potsim2/vdw.py
potsim2/potsimlib.cpython-39-x86_64-linux-gnu.so
potsim2/__init__.py
potsim2/PotGrid.py
potsim2/src/potsimlib.cpp
