Metadata-Version: 2.2
Name: potsim2
Version: 0.3.6
Summary: Simple package to segment and compare protein potential grids
Author-email: Eloy Felix <eloyfelix@gmail.com>
License: MIT
Project-URL: Homepage, https://github.com/chembl/potsim2
Classifier: Development Status :: 3 - Alpha
Classifier: License :: OSI Approved :: MIT License
Classifier: Programming Language :: Python :: 3.9
Classifier: Programming Language :: Python :: 3.10
Classifier: Programming Language :: Python :: 3.11
Classifier: Programming Language :: Python :: 3.12
Classifier: Programming Language :: Python :: 3.13
Classifier: Topic :: Scientific/Engineering :: Chemistry
Requires-Python: >=3.9
License-File: LICENSE
Requires-Dist: MDAnalysis>=2.3.0
Requires-Dist: GridDataFormats>=1.0.1
